banana_image_mcp/__init__.py
banana_image_mcp/server.py
banana_image_mcp/config/__init__.py
banana_image_mcp/config/constants.py
banana_image_mcp/config/settings.py
banana_image_mcp/core/__init__.py
banana_image_mcp/core/exceptions.py
banana_image_mcp/core/progress_tracker.py
banana_image_mcp/core/server.py
banana_image_mcp/core/validation.py
banana_image_mcp/prompts/__init__.py
banana_image_mcp/prompts/design.py
banana_image_mcp/prompts/editing.py
banana_image_mcp/prompts/photography.py
banana_image_mcp/resources/__init__.py
banana_image_mcp/resources/file_metadata.py
banana_image_mcp/resources/operation_status.py
banana_image_mcp/resources/stored_images.py
banana_image_mcp/resources/template_catalog.py
banana_image_mcp/services/__init__.py
banana_image_mcp/services/base_image_service.py
banana_image_mcp/services/enhanced_image_service.py
banana_image_mcp/services/file_image_service.py
banana_image_mcp/services/file_service.py
banana_image_mcp/services/files_api_service.py
banana_image_mcp/services/flash_image_service.py
banana_image_mcp/services/gemini_client.py
banana_image_mcp/services/image_database_service.py
banana_image_mcp/services/image_storage_service.py
banana_image_mcp/services/maintenance_service.py
banana_image_mcp/services/model_selector.py
banana_image_mcp/services/pro_image_service.py
banana_image_mcp/services/template_service.py
banana_image_mcp/tools/__init__.py
banana_image_mcp/tools/generate_image.py
banana_image_mcp/tools/maintenance.py
banana_image_mcp/tools/output_stats.py
banana_image_mcp/tools/upload_file.py
banana_image_mcp/utils/__init__.py
banana_image_mcp/utils/image_utils.py
banana_image_mcp/utils/logging_utils.py
banana_image_mcp/utils/validation_utils.py
banana_image_mcp-1.0.1.dist-info/METADATA
banana_image_mcp-1.0.1.dist-info/WHEEL
banana_image_mcp-1.0.1.dist-info/entry_points.txt
banana_image_mcp-1.0.1.dist-info/licenses/LICENSE
banana_image_mcp-1.0.1.dist-info/RECORD
